{
  "dev": {
    "gateway": "http://112.74.188.206:8888",
    "userId": "1",
    "roleId": "1",
    "menuId": "1",
    "userRoleId": "1",
    "roleMenuId": "1",
    "logId": "1",
    "oauthClientDetailsId": "1",
    "traceId": "",
    "demoUsername": "demo_user",
    "demoPassword": "demo_pass_123",
    "accessToken": ""
  },
  "local": {
    "gateway": "http://127.0.0.1:8888",
    "userId": "1",
    "roleId": "1",
    "menuId": "1",
    "userRoleId": "1",
    "roleMenuId": "1",
    "logId": "1",
    "oauthClientDetailsId": "1",
    "traceId": "",
    "demoUsername": "demo_user",
    "demoPassword": "demo_pass_123",
    "accessToken": ""
  }
}
